lightning_fast/__init__.py
lightning_fast/config.py
lightning_fast/c_structs/__init__.py
lightning_fast/c_structs/custom_structure.py
lightning_fast/c_structs/uthash.py
lightning_fast/c_tools/__init__.py
lightning_fast/c_tools/encoders.pyi
lightning_fast/config_factory/__init__.py
lightning_fast/config_factory/config_constructor.py
lightning_fast/config_factory/simple_directory_collection.py
lightning_fast/config_factory/yaml_example.py
lightning_fast/encoders/__init__.py
lightning_fast/encoders/c_encoders/__init__.py
lightning_fast/encoders/c_encoders/c_label_encoder.py
lightning_fast/encoders/c_encoders/c_utils.py
lightning_fast/encoders/common_encoders/__init__.py
lightning_fast/encoders/common_encoders/common_label_encoder.py
lightning_fast/mongodb/__init__.py
lightning_fast/mongodb/clients/__init__.py
lightning_fast/mongodb/clients/client_descriptor/__init__.py
lightning_fast/mongodb/clients/client_descriptor/base/__init__.py
lightning_fast/mongodb/clients/client_descriptor/base/client_descriptor_base.py
lightning_fast/mongodb/clients/client_descriptor/descriptors/__init__.py
lightning_fast/mongodb/clients/client_descriptor/descriptors/async_client_descriptor.py
lightning_fast/mongodb/clients/client_descriptor/descriptors/sync_client_descriptor.py
lightning_fast/redis_connection/__init__.py
lightning_fast/redis_connection/pool/__init__.py
lightning_fast/redis_connection/pool/base/__init__.py
lightning_fast/redis_connection/pool/base/pool_descriptor_base.py
lightning_fast/redis_connection/pool/descriptors/__init__.py
lightning_fast/redis_connection/pool/descriptors/sync_client_descriptor.py
lightning_fast/tools/__init__.py
lightning_fast/tools/base_tools/__init__.py
lightning_fast/tools/base_tools/ip_tools.py
lightning_fast/tools/dask_tools/__init__.py
lightning_fast/tools/dask_tools/dask_computer.py
lightning_fast/tools/dask_tools/dask_config_controller.py
lightning_fast/tools/dask_tools/dask_reader.py
lightning_fast-0.0.120.dist-info/METADATA
lightning_fast-0.0.120.dist-info/WHEEL
lightning_fast-0.0.120.dist-info/top_level.txt
lightning_fast-0.0.120.dist-info/RECORD
