Metadata-Version: 2.1
Name: lightning-fast
Version: 0.0.120
Summary: Fast Tools
Home-page: https://github.com/xuqiushi/lightning_fast
Author: yingxiongxqs
Author-email: yingxiongxqs@126.com
Classifier: Development Status :: 1 - Planning
Classifier: Programming Language :: Python :: 3.7
Classifier: License :: OSI Approved :: MIT License
Classifier: Operating System :: MacOS :: MacOS X
Classifier: Topic :: Text Processing
Requires-Python: >=3.7
Requires-Dist: pyyaml
Requires-Dist: python-dateutil
Requires-Dist: conan
Provides-Extra: full
Requires-Dist: luigi ; extra == 'full'
Requires-Dist: scikit-learn ; extra == 'full'
Requires-Dist: joblib ; extra == 'full'
Requires-Dist: pandas ; extra == 'full'
Requires-Dist: numpy ; extra == 'full'
Requires-Dist: aiosmtplib ; extra == 'full'
Requires-Dist: python-dateutil ; extra == 'full'
Requires-Dist: pymongo ; extra == 'full'
Requires-Dist: redis ; extra == 'full'
Requires-Dist: motor ; extra == 'full'
